pogrep.py
pogrep-0.1.4.dist-info/LICENSE
pogrep-0.1.4.dist-info/METADATA
pogrep-0.1.4.dist-info/WHEEL
pogrep-0.1.4.dist-info/entry_points.txt
pogrep-0.1.4.dist-info/top_level.txt
pogrep-0.1.4.dist-info/RECORD
