Metadata-Version: 2.1
Name: pogrep
Version: 0.1.4
Summary: Find translations examples by grepping in .po files.
Author-email: Julien Palard <julien@palard.fr>
License: MIT License
Project-URL: Homepage, https://github.com/JulienPalard/pogrep
Classifier: Development Status :: 5 - Production/Stable
Classifier: Intended Audience :: Developers
Classifier: License :: OSI Approved :: MIT License
Classifier: Natural Language :: English
Classifier: Programming Language :: Python :: 3
Classifier: Programming Language :: Python :: 3.6
Classifier: Programming Language :: Python :: 3.7
Classifier: Programming Language :: Python :: 3.8
Requires-Python: >=3.6
License-File: LICENSE
Requires-Dist: regex
Requires-Dist: polib
Requires-Dist: tabulate
